LICENSE
README.md
ak8963.py
mpu6500.py
mpu9250.py
setup.cfg
setup.py
micropython_mpu9250.egg-info/PKG-INFO
micropython_mpu9250.egg-info/SOURCES.txt
micropython_mpu9250.egg-info/dependency_links.txt
micropython_mpu9250.egg-info/top_level.txt