Metadata-Version: 2.1
Name: micropython-mpu9250
Version: 0.4.0
Summary: MicroPython I2C driver for MPU9250 9-axis motion tracking device
Home-page: https://github.com/tuupola/micropython-mpu9250
Author: Mika Tuupola
Author-email: tuupola@appelsiini.net
Maintainer: Mika Tuupola
Maintainer-email: tuupola@appelsiini.net
License: MIT
Keywords: accelerometer,gyro,magnetometer,micropython,i2c
Classifier: Development Status :: 4 - Beta
Classifier: Programming Language :: Python :: Implementation :: MicroPython
Classifier: License :: OSI Approved :: MIT License
License-File: LICENSE
